traffic_light_controller and testbench.v
//====================================================
// FPGA-Based Traffic Light Controller
// With Emergency Priority System
//====================================================

module traffic_light_controller (
    input clk,
    input reset,
    input emergency_A,
    input emergency_B,

    output reg A_red,
    output reg A_yellow,
    output reg A_green,

    output reg B_red,
    output reg B_yellow,
    output reg B_green
);

    // State encoding
    reg [1:0] state;

    parameter A_GREEN  = 2'b00;
    parameter A_YELLOW = 2'b01;
    parameter B_GREEN  = 2'b10;
    parameter B_YELLOW = 2'b11;

    // State register
    always @(posedge clk or posedge reset) begin
        if (reset)
            state <= A_GREEN;
        else begin

            // Emergency priority
            if (emergency_A)
                state <= A_GREEN;

            else if (emergency_B)
                state <= B_GREEN;

            else begin
                case (state)

                    A_GREEN:
                        state <= A_YELLOW;

                    A_YELLOW:
                        state <= B_GREEN;

                    B_GREEN:
                        state <= B_YELLOW;

                    B_YELLOW:
                        state <= A_GREEN;

                    default:
                        state <= A_GREEN;

                endcase
            end
        end
    end

    // Output logic
    always @(*) begin

        // Default: all lights OFF
        A_red    = 0;
        A_yellow = 0;
        A_green  = 0;

        B_red    = 0;
        B_yellow = 0;
        B_green  = 0;

        case (state)

            // Road A GREEN, Road B RED
            A_GREEN: begin
                A_green = 1;
                B_red   = 1;
            end

            // Road A YELLOW, Road B RED
            A_YELLOW: begin
                A_yellow = 1;
                B_red    = 1;
            end

            // Road B GREEN, Road A RED
            B_GREEN: begin
                A_red   = 1;
                B_green = 1;
            end

            // Road B YELLOW, Road A RED
            B_YELLOW: begin
                A_red    = 1;
                B_yellow = 1;
            end

            default: begin
                A_red = 1;
                B_red = 1;
            end

        endcase
    end

endmodule


//====================================================
// TESTBENCH
//====================================================

module tb;

    reg clk;
    reg reset;
    reg emergency_A;
    reg emergency_B;

    wire A_red;
    wire A_yellow;
    wire A_green;

    wire B_red;
    wire B_yellow;
    wire B_green;

    // Instantiate the traffic light controller
    traffic_light_controller uut (
        .clk(clk),
        .reset(reset),
        .emergency_A(emergency_A),
        .emergency_B(emergency_B),

        .A_red(A_red),
        .A_yellow(A_yellow),
        .A_green(A_green),

        .B_red(B_red),
        .B_yellow(B_yellow),
        .B_green(B_green)
    );

    //================================================
    // CLOCK
    //================================================
    initial begin
        clk = 0;
        forever #5 clk = ~clk;
    end

    //================================================
    // WAVEFORM DUMP
    //================================================
    initial begin
        $dumpfile("dump.vcd");
        $dumpvars(0, tb);
    end

    //================================================
    // TEST
    //================================================
    initial begin

        // Initial values
        reset = 1;
        emergency_A = 0;
        emergency_B = 0;

        #10;

        // Release reset
        reset = 0;

        // Normal operation
        #20;

        // Emergency for Road B
        emergency_B = 1;
        #20;
        emergency_B = 0;

        // Normal operation
        #30;

        // Emergency for Road A
        emergency_A = 1;
        #20;
        emergency_A = 0;

        // Continue normal operation
        #30;

        $finish;
    end

    //================================================
    // DISPLAY OUTPUT
    //================================================
    initial begin
        $monitor(
            "TIME=%0t | A(RYG)=%b%b%b | B(RYG)=%b%b%b | Emergency A=%b B=%b",
            $time,
            A_red, A_yellow, A_green,
            B_red, B_yellow, B_green,
            emergency_A, emergency_B
        );
    end

endmodule

traffic_light.vcd
$date
	Thu Sep  3 18:06:17 2026
$end
$version
	Icarus Verilog
$end
$timescale
	1s
$end
$scope module tb $end
$var wire 1 ! B_yellow $end
$var wire 1 " B_red $end
$var wire 1 # B_green $end
$var wire 1 $ A_yellow $end
$var wire 1 % A_red $end
$var wire 1 & A_green $end
$var reg 1 ' clk $end
$var reg 1 ( emergency_A $end
$var reg 1 ) emergency_B $end
$var reg 1 * reset $end
$scope module uut $end
$var wire 1 ' clk $end
$var wire 1 ( emergency_A $end
$var wire 1 ) emergency_B $end
$var wire 1 * reset $end
$var parameter 2 + A_GREEN $end
$var parameter 2 , A_YELLOW $end
$var parameter 2 - B_GREEN $end
$var parameter 2 . B_YELLOW $end
$var reg 1 & A_green $end
$var reg 1 % A_red $end
$var reg 1 $ A_yellow $end
$var reg 1 # B_green $end
$var reg 1 " B_red $end
$var reg 1 ! B_yellow $end
$var reg 2 / state [1:0] $end
$upscope $end
$upscope $end
$enddefinitions $end
$comment Show the parameter values. $end
$dumpall
b11 .
b10 -
b1 ,
b0 +
$end
#0
$dumpvars
b0 /
1*
0)
0(
0'
1&
0%
0$
0#
1"
0!
$end
#5
1'
#10
0'
0*
#15
1$
1"
0&
b1 /
1'
#20
0'
#25
1#
1%
0"
0$
b10 /
1'
#30
0'
1)
#35
1'
#40
0'
#45
1'
#50
0'
0)
#55
1!
0#
1%
b11 /
1'
#60
0'
#65
1"
1&
0!
0%
b0 /
1'
#70
0'
#75
1$
1"
0&
b1 /
1'
#80
0'
1(
#85
1&
1"
0$
b0 /
1'
#90
0'
#95
1'
#100
0'
0(
#105
1$
1"
0&
b1 /
1'
#110
0'
#115
1#
1%
0"
0$
b10 /
1'
#120
0'
#125
1!
0#
1%
b11 /
1'
